docgen/__init__.py
docgen/generator/__init__.py
docgen/generator/cst_parser.py
docgen/generator/loader.py
docgen/generator/writer.py
docgen/templates/__init__.py
docgen/templates/base.py
docgen/templates/extended.py
py_docstrings-0.1.0.dist-info/METADATA
py_docstrings-0.1.0.dist-info/WHEEL
py_docstrings-0.1.0.dist-info/entry_points.txt
py_docstrings-0.1.0.dist-info/top_level.txt
py_docstrings-0.1.0.dist-info/RECORD
