Metadata-Version: 2.4
Name: py-docstrings
Version: 0.1.0
Summary: Automatically generate NumPy-style docstrings
Author-email: Nimish Purohit <nimishpurohitn@gmail.com>
License-Expression: MIT
Project-URL: Homepage, https://github.com/Nimish-4/py-docstrings
Project-URL: Repository, https://github.com/Nimish-4/py-docstrings
Keywords: docstring,documentation,cli,libcst
Classifier: Programming Language :: Python :: 3
Classifier: Intended Audience :: Developers
Classifier: Topic :: Software Development :: Documentation
Requires-Python: >=3.9
Requires-Dist: click
Requires-Dist: libcst
Requires-Dist: pathspec
Provides-Extra: dev
Requires-Dist: pytest; extra == "dev"
